jvstats/__init__.py
jvstats/console.py
jvstats-0.1.4.data/data/data/test1.csv
jvstats-0.1.4.dev0.dist-info/LICENSE
jvstats-0.1.4.dev0.dist-info/METADATA
jvstats-0.1.4.dev0.dist-info/WHEEL
jvstats-0.1.4.dev0.dist-info/entry_points.txt
jvstats-0.1.4.dev0.dist-info/top_level.txt
jvstats-0.1.4.dev0.dist-info/RECORD
