Metadata-Version: 2.1
Name: jvstats
Version: 0.1.4.dev0
Summary: UNKNOWN
Home-page: UNKNOWN
Author: Jaime Viloria
Author-email: jaime.viloria@gmail.com
License: MIT
Platform: UNKNOWN
Requires-Python: >=3.5
Requires-Dist: click
